trytond/modules/pim_calendar/README.rst
trytond/modules/pim_calendar/__init__.py
trytond/modules/pim_calendar/calendar2.py
trytond/modules/pim_calendar/calendar2.xml
trytond/modules/pim_calendar/const.py
trytond/modules/pim_calendar/events.py
trytond/modules/pim_calendar/events.xml
trytond/modules/pim_calendar/exportcal.py
trytond/modules/pim_calendar/exportcal.xml
trytond/modules/pim_calendar/icon.xml
trytond/modules/pim_calendar/importwiz.py
trytond/modules/pim_calendar/importwiz.xml
trytond/modules/pim_calendar/menu.xml
trytond/modules/pim_calendar/message.xml
trytond/modules/pim_calendar/model.py
trytond/modules/pim_calendar/role_admin.xml
trytond/modules/pim_calendar/role_cal_user.xml
trytond/modules/pim_calendar/tryton.cfg
trytond/modules/pim_calendar/versiondep.txt
trytond/modules/pim_calendar/visitors.py
trytond/modules/pim_calendar/visitors.xml
trytond/modules/pim_calendar/icon/calendar-month-quiet.svg
trytond/modules/pim_calendar/icon/day-12.svg
trytond/modules/pim_calendar/locale/de.po
trytond/modules/pim_calendar/locale/en.po
trytond/modules/pim_calendar/tests/__init__.py
trytond/modules/pim_calendar/tests/calendar.py
trytond/modules/pim_calendar/tests/events.py
trytond/modules/pim_calendar/tests/ical_data.py
trytond/modules/pim_calendar/tests/importwiz.py
trytond/modules/pim_calendar/tests/test_module.py
trytond/modules/pim_calendar/tests/testlib.py
trytond/modules/pim_calendar/tests/visitor.py
trytond/modules/pim_calendar/view/calendar_form.xml
trytond/modules/pim_calendar/view/calendar_tree.xml
trytond/modules/pim_calendar/view/event_calendar.xml
trytond/modules/pim_calendar/view/event_calendar_allday.xml
trytond/modules/pim_calendar/view/event_form.xml
trytond/modules/pim_calendar/view/event_tree.xml
trytond/modules/pim_calendar/view/import_event_form.xml
trytond/modules/pim_calendar/view/visitor_form.xml
trytond/modules/pim_calendar/view/visitor_tree.xml
mds_pim_calendar-7.0.2.dist-info/METADATA
mds_pim_calendar-7.0.2.dist-info/WHEEL
mds_pim_calendar-7.0.2.dist-info/entry_points.txt
mds_pim_calendar-7.0.2.dist-info/top_level.txt
mds_pim_calendar-7.0.2.dist-info/RECORD
