Metadata-Version: 2.1
Name: mds-pim-calendar
Version: 7.0.2
Summary: a Tryton calendar module
Home-page: https://www.m-ds.de/
Author: m-ds
Author-email: service@m-ds.de
License: GPL-3
Keywords: tryton time calendar event
Platform: UNKNOWN
Classifier: Development Status :: 5 - Production/Stable
Classifier: Environment :: Plugins
Classifier: Framework :: Tryton
Classifier: Intended Audience :: Developers
Classifier: Intended Audience :: Customer Service
Classifier: Intended Audience :: Information Technology
Classifier: Intended Audience :: Financial and Insurance Industry
Classifier: Topic :: Office/Business
Classifier: Topic :: Office/Business :: Financial :: Accounting
Classifier: Natural Language :: German
Classifier: Natural Language :: English
Classifier: Operating System :: OS Independent
Classifier: License :: OSI Approved :: GNU General Public License (GPL)
Classifier: Programming Language :: Python :: 3.7
Classifier: Programming Language :: Python :: 3.8
Classifier: Programming Language :: Python :: 3.9
Requires-Dist: icalendar
Requires-Dist: pytz
Requires-Dist: trytond (<7.1,>=7.0)
